yara_procdump.so
yara_procdump_python-0.1.0.post7.dist-info/DESCRIPTION.rst
yara_procdump_python-0.1.0.post7.dist-info/METADATA
yara_procdump_python-0.1.0.post7.dist-info/RECORD
yara_procdump_python-0.1.0.post7.dist-info/WHEEL
yara_procdump_python-0.1.0.post7.dist-info/metadata.json
yara_procdump_python-0.1.0.post7.dist-info/top_level.txt
